evomo_mqtt/__init__.py
evomo_mqtt-1.0.2.dist-info/LICENSE
evomo_mqtt-1.0.2.dist-info/METADATA
evomo_mqtt-1.0.2.dist-info/WHEEL
evomo_mqtt-1.0.2.dist-info/top_level.txt
evomo_mqtt-1.0.2.dist-info/RECORD
