Metadata-Version: 2.1
Name: evomo-mqtt
Version: 1.0.2
Summary: A Python Library to simplify connection to Evomo IoT Platform
Home-page: https://github.com/bhaktiyudha/evomo_mqtt
Author: Evomo Support Team
Author-email: info@jeager.io
License: UNKNOWN
Platform: UNKNOWN
Classifier: Programming Language :: Python :: 3
Classifier: Programming Language :: Python :: 2.7
Classifier: License :: OSI Approved :: MIT License
Classifier: Operating System :: OS Independent
Requires-Dist: paho-mqtt
